[
  {
    "name": "Media Server Licenses",
    "id": "MediaServer-licenses",
    "destination": "Licenses/MediaServer",
    "filename": "mediaservertest_40_0?core*_prod_vm.i3lic",
    "locations":
    [
      {
        "location": "APAC",
        "network":  "172.22.[0-9]+.[0-9]+/[0-9]+",
        "need_auth": true,
        "url": "smb://indytestfiles/Testlab_Software/MediaServerTestLicenses/production_license_with_vm_feature_enabled/"
      },
      {
        "location": "EMEA",
        "network":  "172.30.[0-9]+.[0-9]+/[0-9]+",
        "need_auth": true,
        "url": "smb://indytestfiles/Testlab_Software/MediaServerTestLicenses/production_license_with_vm_feature_enabled/"
      },
      {
        "location": "HQ",
        "network":  "172.17.[0-9]+.[0-9]+/[0-9]+",
        "need_auth": true,
        "url": "smb://indytestfiles/Testlab_Software/MediaServerTestLicenses/production_license_with_vm_feature_enabled/"
      },
      {
        "location": "Intranet",
        "network":  ".*",
        "need_auth": true,
        "vpn": ".*vpn.inin.com",
        "url": "smb://indytestfiles/Testlab_Software/MediaServerTestLicenses/production_license_with_vm_feature_enabled/"
      }
    ]
  },
  {
    "name": "Windows 2012R2 Evaluation",
    "id": "Windows_2012R2",
    "checksum": { "type": "MD5", "value": "458ff91f8abc21b75cb544744bf92e6a" },
    "filename": "9600.16384.WINBLUE_RTM.130821-1623_X64FRE_SERVER_EVAL_EN-US-IRM_SSS_X64FREE_EN-US_DV5.ISO",
    "locations":
    [
      {
        "location": "APAC",
        "network":  "172.22.(16|32|40|80|81).[0-9]+/[0-9]+",
        "need_auth": true,
        "url": "smb://apac.inin.com/Software/Microsoft/Evaluation/WindowsServer/2012R2/"
      },
      {
        "location": "EMEA",
        "network":  "172.30.[0-9]+.[0-9]+/[0-9]+",
        "need_auth": true,
        "url": "smb://emea.inin.com/Software/Microsoft/Evaluation/WindowsServer/2012R2/"
      },
      {
        "location": "Internet",
        "network":  ".*",
        "has_resume": true,
        "bits": false,
        "url": "http://download.microsoft.com/download/6/2/A/62A76ABB-9990-4EFC-A4FE-C7D698DAEB96/"
      }
    ]
  },
  {
    "name": "SQL 2014 Express",
    "id": "SQL_2014",
    "checksum": { "type": "MD5", "value": "3bb7d34aaf063b73ac92d31aad896ba6" },
    "filename": "SQLEXPRWT_x64_ENU.exe",
    "locations":
    [
      {
        "location": "APAC",
        "network":  "172.22.(16|32|40|80|81).[0-9]+/[0-9]+",
        "need_auth": true,
        "url": "smb://apac.inin.com/Software/Microsoft/Evaluation/SQLServer/2014/"
      },
      {
        "location": "EMEA",
        "network":  "172.30.[0-9]+.[0-9]+/[0-9]+",
        "need_auth": true,
        "url": "smb://emea.inin.com/Software/Microsoft/Evaluation/SQLServer/2014/"
      },
      {
        "location": "Internet",
        "network":  ".*",
        "has_resume": true,
        "bits": false,
        "url": "http://download.microsoft.com/download/E/A/E/EAE6F7FC-767A-4038-A954-49B8B05D04EB/ExpressAndTools%2064BIT/"
      }
    ]
  },
  {
    "name": "CIC 2016R1",
    "id": "CIC_2016R1",
    "checksum": { "type": "MD5", "value": "46D62B7237B2D3BBD2794DD1812BDAAE" },
    "filename": "CIC_2016_R1.iso",
    "locations":
    [
      {
        "location": "APAC",
        "network":  "172.22.(16|32|40|80|81).[0-9]+/[0-9]+",
        "need_auth": true,
        "url": "smb://apac.inin.com/Software/ININ/Interaction%20Center/2016R1/"
      },
      {
        "location": "EMEA",
        "network":  "172.30.[0-9]+.[0-9]+/[0-9]+",
        "need_auth": true,
        "url": "smb://emea.inin.com/Software/ININ/Interaction%20Center/2016R1/"
      },
      {
        "location": "Internet",
        "network":  ".*",
        "has_resume": true,
        "need_auth": true,
        "type": "akamai",
        "url": "http://www2.inin.com/AkamaiFileHandler/File.ashx?path=/Service%20Updates/CIC/packaging.2016r1/P00/"
      }
    ]
  },
  {
    "name": "CIC 2016R1 Patch 2",
    "id": "CIC_2016R1_Patch2",
    "checksum": { "type": "MD5", "value": "DE10DACC542E292710934B7004EA4C80" },
    "filename": "CIC_2016_R1_Patch2.iso",
    "locations":
    [
      {
        "location": "APAC",
        "network":  "172.22.(16|32|40|80|81).[0-9]+/[0-9]+",
        "need_auth": true,
        "url": "smb://apac.inin.com/Software/ININ/Interaction%20Center/2016R1/"
      },
      {
        "location": "EMEA",
        "network":  "172.30.[0-9]+.[0-9]+/[0-9]+",
        "need_auth": true,
        "url": "smb://emea.inin.com/Software/ININ/Interaction%20Center/2016R1/"
      },
      {
        "location": "Internet",
        "network":  ".*",
        "has_resume": true,
        "need_auth": true,
        "type": "akamai",
        "url": "http://www2.inin.com/AkamaiFileHandler/File.ashx?path=/Service%20Updates/CIC/packaging.2016r1/P02/"
      }
    ]
  },
  {
    "name": "Old CIC 2015 releases",
    "id": "CIC_2015R1,R2,R3,R4",
    "destination": "CIC_2015_R[1-4].iso*",
    "action": "delete"
  },
  {
    "name": "Old CIC 2015 Patches",
    "id": "CIC_2015R1,R2,R3,R4_Patches",
    "destination": "CIC_2015_R[1-4]_Patch*.iso*",
    "action": "delete"
  },
  {
    "name": "Dialer 2016R1",
    "id": "Dialer_2016R1",
    "checksum": { "type": "MD5", "value": "7B6D941B370C56FA26BE57600400A43F" },
    "filename": "Dialer_2016_R1.iso",
    "locations":
    [
      {
        "location": "APAC",
        "network":  "172.22.(16|32|40|80|81).[0-9]+/[0-9]+",
        "need_auth": true,
        "url": "smb://apac.inin.com/Software/ININ/Interaction%20Dialer/2016R1/"
      },
      {
        "location": "EMEA",
        "network":  "172.30.[0-9]+.[0-9]+/[0-9]+",
        "need_auth": true,
        "url": "smb://emea.inin.com/Software/ININ/Interaction%20Dialer/2016R1/"
      },
      {
        "location": "Internet",
        "network":  ".*",
        "has_resume": true,
        "need_auth": true,
        "type": "akamai",
        "url": "http://www2.inin.com/AkamaiFileHandler/File.ashx?path=/Service%20Updates/Interaction_Dialer/2016r1/P00/"
      }
    ]
  },
  {
    "name": "Dialer 2016R1 Patch 2",
    "id": "Dialer_2016R1_Patch2",
    "checksum": { "type": "MD5", "value": "3BB3EBE4C4C985FDAAAEFAA1243BA860" },
    "filename": "Dialer_2016_R1_Patch2.iso",
    "locations":
    [
      {
        "location": "APAC",
        "network":  "172.22.(16|32|40|80|81).[0-9]+/[0-9]+",
        "need_auth": true,
        "url": "smb://apac.inin.com/Software/ININ/Interaction%20Dialer/2016R1/"
      },
      {
        "location": "EMEA",
        "network":  "172.30.[0-9]+.[0-9]+/[0-9]+",
        "need_auth": true,
        "url": "smb://emea.inin.com/Software/ININ/Interaction%20Dialer/2016R1/"
      },
      {
        "location": "Internet",
        "network":  ".*",
        "has_resume": true,
        "need_auth": true,
        "type": "akamai",
        "url": "http://www2.inin.com/AkamaiFileHandler/File.ashx?path=/Service%20Updates/Interaction_Dialer/2016r1/P02/"
      }
    ]
  },
  {
    "name": "Old Dialer 2015 releases",
    "id": "Dialer_2015R1,R2,R3,R4",
    "destination": "Dialer_2015_R[1-4].iso*",
    "action": "delete"
  },
  {
    "name": "Old Dialer 2015 Patches",
    "id": "Dialer_2015R1,R2,R3,R4_Patches",
    "destination": "Dialer_2015_R[1-4]_Patch*.iso*",
    "action": "delete"
  },
  {
    "name": "Web Applications 2016R1",
    "id": "WebApplications_2016R1",
    "checksum": { "type": "MD5", "value": "C6B7062F92309FF03B35EC6F9659FBAD" },
    "filename": "CIC_Web_Applications_2016_R1.zip",
    "locations":
    [
      {
        "location": "APAC",
        "network":  "172.22.(16|32|40|80|81).[0-9]+/[0-9]+",
        "need_auth": true,
        "url": "smb://apac.inin.com/Software/ININ/Web%20Applications/2016R1/"
      },
      {
        "location": "EMEA",
        "network":  "172.30.[0-9]+.[0-9]+/[0-9]+",
        "need_auth": true,
        "url": "smb://emea.inin.com/Software/ININ/Web%20Applications/2016R1/"
      },
      {
        "location": "Internet",
        "network":  ".*",
        "has_resume": true,
        "need_auth": true,
        "type": "akamai",
        "url": "http://www2.inin.com/AkamaiFileHandler/File.ashx?path=/Service%20Updates/CIC_Web_Applications/IC_Web_Packaging_2016r1/P00/"
      }
    ]
  },
  {
    "name": "Web Applications 2016R1 Patch 2",
    "id": "WebApplications_2016R1_Patch2",
    "checksum": { "type": "MD5", "value": "DDF194B4F32758DEA5E03ABEB5851FA0" },
    "filename": "CIC_Web_Applications_2016_R1_Patch_2.zip",
    "locations":
    [
      {
        "location": "APAC",
        "network":  "172.22.(16|32|40|80|81).[0-9]+/[0-9]+",
        "need_auth": true,
        "url": "smb://apac.inin.com/Software/ININ/Web%20Applications/2016R1/"
      },
      {
        "location": "EMEA",
        "network":  "172.30.[0-9]+.[0-9]+/[0-9]+",
        "need_auth": true,
        "url": "smb://emea.inin.com/Software/ININ/Web%20Applications/2016R1/"
      },
      {
        "location": "Internet",
        "network":  ".*",
        "has_resume": true,
        "need_auth": true,
        "type": "akamai",
        "url": "http://www2.inin.com/AkamaiFileHandler/File.ashx?path=/Service%20Updates/CIC_Web_Applications/IC_Web_Packaging_2016r1/P02/"
      }
    ]
  },
  {
    "name": "Old Web Applications 2015 releases",
    "id": "WebApplications_2015R1,R2,R3,R4",
    "destination": "CIC_Web_Applications_2015_R[1-4].zip*",
    "action": "delete"
  },
  {
    "name": "Old Web Applications 2015 Patches",
    "id": "WebApplications_2015R1,R2,R3,R4_Patches",
    "destination": "CIC_Web_Applications_2015_R[1-4]_Patch*.zip*",
    "action": "delete"
  },
  {
    "name": "IC Server 2015R2",
    "id": "ICServer_2015R2",
    "destination": "ICServer_2015_R2.msi*",
    "action": "delete"
  },
  {
    "name": "IC Firmware 2015R2",
    "id": "ICFirmware_2015R2",
    "destination": "InteractionFirmware_2015_R2.msi*",
    "action": "delete"
  },
  {
    "name": "MediaServer 2015R2",
    "id": "MediaServer_2015R2",
    "destination": "MediaServer_2015_R2.msi*",
    "action": "delete"
  }
]
